<?xml version="1.0"?> <annotation> <folder>images</folder> <filename>IMG20190702121508.jpg</filename> <path>images/IMG20190702121508.jpg</path> <source> <database>Unknown</database> </source> <size> <width>800</width> <height>600</height> <depth>3</depth> </size> <segmented>0</segmented> <object> <name>colony</name> <pose>Unspecified</pose> <truncated>0</truncated> <difficult>0</difficult> <bndbox> <xmin>486.9999694824219</xmin> <ymin>356</ymin> <xmax>508.9999694824219</xmax> <ymax>373</ymax> </bndbox> </object> <object> <name>colony</name> <pose>Unspecified</pose> <truncated>0</truncated> <difficult>0</difficult> <bndbox> <xmin>437.9999694824219</xmin> <ymin>258</ymin> <xmax>456.9999694824219</xmax> <ymax>276</ymax> </bndbox> </object> <object> <name>colony</name> <pose>Unspecified</pose> <truncated>0</truncated> <difficult>0</difficult> <bndbox> <xmin>263.9999694824219</xmin> <ymin>241</ymin> <xmax>278.9999694824219</xmax> <ymax>257</ymax> </bndbox> </object> <object> <name>colony</name> <pose>Unspecified</pose> <truncated>0</truncated> <difficult>0</difficult> <bndbox> <xmin>277.9999694824219</xmin> <ymin>282</ymin> <xmax>294.9999694824219</xmax> <ymax>302</ymax> </bndbox> </object> <object> <name>colony</name> <pose>Unspecified</pose> <truncated>0</truncated> <difficult>0</difficult> <bndbox> <xmin>259.9999694824219</xmin> <ymin>180</ymin> <xmax>278.9999694824219</xmax> <ymax>197</ymax> </bndbox> </object> <object> <name>colony</name> <pose>Unspecified</pose> <truncated>0</truncated> <difficult>0</difficult> <bndbox> <xmin>295.9999694824219</xmin> <ymin>208</ymin> <xmax>308.9999694824219</xmax> <ymax>225</ymax> </bndbox> </object> <object> <name>colony</name> <pose>Unspecified</pose> <truncated>0</truncated> <difficult>0</difficult> <bndbox> <xmin>210.99996948242188</xmin> <ymin>291</ymin> <xmax>225.99996948242188</xmax> <ymax>308</ymax> </bndbox> </object> <object> <name>colony</name> <pose>Unspecified</pose> <truncated>0</truncated> <difficult>0</difficult> <bndbox> <xmin>278.9999694824219</xmin> <ymin>367</ymin> <xmax>293.9999694824219</xmax> <ymax>383</ymax> </bndbox> </object> <object> <name>colony</name> <pose>Unspecified</pose> <truncated>0</truncated> <difficult>0</difficult> <bndbox> <xmin>316.9999694824219</xmin> <ymin>416</ymin> <xmax>333.9999694824219</xmax> <ymax>438</ymax> </bndbox> </object> <object> <name>colony</name> <pose>Unspecified</pose> <truncated>0</truncated> <difficult>0</difficult> <bndbox> <xmin>433.9999694824219</xmin> <ymin>449</ymin> <xmax>452.9999694824219</xmax> <ymax>466</ymax> </bndbox> </object> <object> <name>colony</name> <pose>Unspecified</pose> <truncated>0</truncated> <difficult>0</difficult> <bndbox> <xmin>395.9999694824219</xmin> <ymin>456</ymin> <xmax>407.9999694824219</xmax> <ymax>472</ymax> </bndbox> </object> <object> <name>colony</name> <pose>Unspecified</pose> <truncated>0</truncated> <difficult>0</difficult> <bndbox> <xmin>401.9999694824219</xmin> <ymin>486</ymin> <xmax>416.9999694824219</xmax> <ymax>503</ymax> </bndbox> </object> </annotation>
